chaosmath/__init__.py
chaosmath/cli.py
chaosmath/core.py
chaosmath/example.py
chaosmath/excuses.py
chaosmath-0.2.2.dist-info/licenses/LICENSE
chaosmath-0.2.2.dist-info/METADATA
chaosmath-0.2.2.dist-info/WHEEL
chaosmath-0.2.2.dist-info/entry_points.txt
chaosmath-0.2.2.dist-info/top_level.txt
chaosmath-0.2.2.dist-info/RECORD
