Metadata-Version: 2.4
Name: chaosmath
Version: 0.2.2
Summary: Math functions that almost work
Author: EazyFencer
License: MIT License
Project-URL: Homepage, https://github.com/prathambhandary/chaosmath
Keywords: chaos,math,fun,memes,excuses,random,useless,timepass,bored,explore
Classifier: Programming Language :: Python :: 3
Classifier: Topic :: Software Development :: Libraries
Classifier: Intended Audience :: Developers
Requires-Python: >=3.8
License-File: LICENSE
Dynamic: license-file
